labelme_stats/cli.py
labelme_stats-1.0.4.dist-info/METADATA
labelme_stats-1.0.4.dist-info/WHEEL
labelme_stats-1.0.4.dist-info/entry_points.txt
labelme_stats-1.0.4.dist-info/top_level.txt
labelme_stats-1.0.4.dist-info/RECORD
