Metadata-Version: 2.1
Name: labelme_stats
Version: 1.0.4
Summary: Labelme statistics
Author-email: Bryt <bryt.xin.li@gmail.com>
Project-URL: Homepage, https://github.com/xin-at-marathon/pypi
Project-URL: Issues, https://github.com/xin-at-marathon/pypi/issues
Classifier: Programming Language :: Python :: 3
Classifier: License :: OSI Approved :: MIT License
Classifier: Operating System :: OS Independent
Requires-Python: >=3.6
